saintess/__init__.py
saintess/bot.py
saintess/config_loader.py
saintess/decos.py
saintess-0.9.3.dist-info/METADATA
saintess-0.9.3.dist-info/WHEEL
saintess-0.9.3.dist-info/top_level.txt
saintess-0.9.3.dist-info/RECORD
