Metadata-Version: 2.4
Name: saintess
Version: 0.9.3
Summary: Official wrapper for Discord API.
Home-page: https://github.com/yourusername/saintess
Author: Saint Official
Author-email: support@saint.xxx
Classifier: Programming Language :: Python :: 3
Classifier: License :: OSI Approved :: MIT License
Classifier: Operating System :: OS Independent
Classifier: Development Status :: 4 - Beta
Requires-Python: >=3.8
Requires-Dist: discord.py
Dynamic: author
Dynamic: author-email
Dynamic: classifier
Dynamic: description
Dynamic: description-content-type
Dynamic: home-page
Dynamic: requires-dist
Dynamic: requires-python
Dynamic: summary
